D_flipflop/D_flipflop.v
module D_flipflop(input clk, input d, output reg q, output qbar);
always @(posedge clk)
    begin
    q<=d;
    end
    assign qbar=~q;
endmodule

D_flipflop/D_flipflop_tb.v
`timescale 1ns/1ns
`include"D_flipflop.v"
module dff();
reg d;
reg clk;
wire q;
wire qbar;
D_flipflop dut(.d(d), .clk(clk), .q(q), .qbar(qbar));
always #5 clk=~clk;
initial  
    begin 
           $dumpfile("D_FlipFlop.vcd");
           $dumpvars(1,dff);
        clk=0;
        #10 d=0;
        #10 d=1;
        #10 d=0;
        #10 d=1;
        #10 d=0;
#10 d=1;
        #10 d=0;
        #10 d=1;
        $finish;
    end

initial begin
  $monitor("At %t: d = %b, q = %b, qbar = %b", $time, d, q, qbar);
end

endmodule

D_flipflop/D_FlipFlop.vcd
$date
	Sun Jul 07 14:22:08 2024
$end
$version
	Icarus Verilog
$end
$timescale
	1ns
$end
$scope module dff $end
$var wire 1 ! q $end
$var wire 1 " qbar $end
$var reg 1 # clk $end
$var reg 1 $ d $end
$upscope $end
$enddefinitions $end
#0
$dumpvars
x$
0#
x"
x!
$end
#5
1#
#10
0#
0$
#15
1"
0!
1#
#20
0#
1$
#25
0"
1!
1#
#30
0#
0$
#35
1"
0!
1#
#40
0#
1$
#45
0"
1!
1#
#50
0#
0$
#55
1"
0!
1#
#60
0#
1$
#65
0"
1!
1#
#70
0#
0$
#75
1"
0!
1#
#80
0#
1$
