Half_adder/Half_adder.v
module half_adder(input a,b, output sum, cout);
assign sum= a^b;
assign cout=a&b;
endmodule

Half_adder/Half_adder_tb.v
`timescale 1ns / 1ps 
`include"Half_adder.v"
module ha_tb();
reg a,b;
wire s,cout;
half_adder ha(a,b,s,cout);
initial begin
     $dumpfile("Half_adder.vcd");
    $dumpvars(1,ha_tb);
 $monitor("At time %0t: a=%b b=%b, sum=%b, carry=%b",$time, a,b,s,cout);
 a = 0; b = 0;
 #1;
 a = 0; b = 1;
 #1;
 a = 1; b = 0;
 #1;
 a = 1; b = 1;
 a = 1; b = 0;
 #1;
 a = 0; b = 1;
 a = 0; b = 0;
 #1;
 a = 0; b = 1;
 a = 1; b = 1;
 #1;
 a = 1; b = 1;
a = 0; b = 0;
 #1;
 a = 0; b = 1;
 end
endmodule

Half_adder/Half_adder.vcd
$date
	Sat Jul 13 12:39:32 2024
$end
$version
	Icarus Verilog
$end
$timescale
	1ps
$end
$scope module ha_tb $end
$var wire 1 ! cout $end
$var wire 1 " s $end
$var reg 1 # a $end
$var reg 1 $ b $end
$upscope $end
$enddefinitions $end
#0
$dumpvars
0$
0#
0"
0!
$end
#1000
1"
1$
#2000
0$
1#
#3000
0$
#4000
0"
0$
0#
#5000
1!
1#
1$
#6000
0!
0$
0#
#7000
1"
1$
