Full_adder using half adder/Full_adder_using_half_adder.v
module half_addr(input a, b, output s, c);
 assign s = a^b;
 assign c = a & b;
endmodule
module full_adder_2(input a, b, cin, output s_out, c_out);
 wire s, c0, c1;
 half_addr HA1 (a, b, s, c0);
 half_addr HA2 (s, cin, s_out, c1);
 
 assign c_out = c0 | c1;
endmodule

Full_adder using half adder/FA_using_HA_tb.v
`timescale 1ns / 1ps 
`include"Full_adder_using_half_adder.v"
module tb_FA();
 reg a, b, c;
 wire s, c_out;
 
 full_adder_2 fa(a, b, c, s, c_out);
 
 initial begin
        $dumpfile("Full_adder_using_half_adder.vcd");
    $dumpvars(1,tb_FA);
 $monitor("At time %0t: a=%b b=%b, cin=%b, sum=%b, carry=%b",$time,
a,b,c,s,c_out);
 a = 0; b = 0; c = 0; #1;
 a = 0; b = 0; c = 1; #1;
 a = 0; b = 1; c = 0; #1;
 a = 0; b = 1; c = 1; #1;
 a = 1; b = 0; c = 0; #1;
 a = 1; b = 0; c = 1; #1;
 a = 1; b = 1; c = 0; #1;
 a = 1; b = 1; c = 1;
 end
endmodule

Full_adder using half adder/Full_adder_using_half_adder.vcd
$date
	Sat Jul 13 13:13:28 2024
$end
$version
	Icarus Verilog
$end
$timescale
	1ps
$end
$scope module tb_FA $end
$var wire 1 ! c_out $end
$var wire 1 " s $end
$var reg 1 # a $end
$var reg 1 $ b $end
$var reg 1 % c $end
$upscope $end
$enddefinitions $end
#0
$dumpvars
0%
0$
0#
0"
0!
$end
#1000
1"
1%
#2000
0%
1$
#3000
1!
0"
1%
#4000
0!
1"
0%
0$
1#
#5000
1!
0"
1%
#6000
0%
1$
#7000
1"
1%
