T_flipflop/T_flipflop.v
module t_ff (input clk,input reset, input t,output reg q);

always @(posedge clk) begin
  if (reset) 
    q <= 1'b0;
  else 
    q <= ~q;
    
  if (t)
    q <= ~q;
end

endmodule

T_flipflop/T_flipflop_tb.v
`timescale 1ns / 1ps 
`include"T_flipflop.v"

module T_flipflop_tb();

  reg t;
  reg clk;
  reg reset;
  wire q;

  t_ff dut ( .t(t), .clk(clk), .reset(reset), .q(q) );


  always begin
    $dumpfile("T_FlipFlop.vcd");
    $dumpvars(1,T_flipflop_tb);
    clk = 0;
    #5; 
    clk = 1;
    #5;
  end

  initial begin
    t = 0;
    reset = 0;

    reset = 1;
    #10; 
    reset = 0;
    $display("Time T clk rst Q");
    $monitor("%2t %b %b %b %b", $time, t, clk, reset, q);

    t = 1; #10; 
    t = 0; #10;

    reset = 1; #10;
    reset = 0;

    t = 1; #10;
    t = 0; #10;

    $finish;
  end

endmodule

T_flipflop/T_FlipFlop.vcd
$date
	Sun Jul 07 14:42:30 2024
$end
$version
	Icarus Verilog
$end
$timescale
	1ps
$end
$scope module T_flipflop_tb $end
$var wire 1 ! q $end
$var reg 1 " clk $end
$var reg 1 # reset $end
$var reg 1 $ t $end
$upscope $end
$enddefinitions $end
#0
$dumpvars
0$
1#
0"
x!
$end
#5000
0!
1"
#10000
0"
1$
0#
#15000
1!
1"
#20000
0"
0$
#25000
0!
1"
#30000
0"
1#
#35000
1"
#40000
0"
1$
0#
#45000
1!
1"
#50000
0"
0$
#55000
0!
1"
