Full_adder/Full_adder.v
module full_adder(input a , b , cin, output sum, cout );
assign sum=a^b^cin;
  assign cout= (a & b) | (b & cin) | (a & cin);
endmodule

Full_adder/Full_adder_tb.v
`timescale 1ns / 1ps 
`include"Full_adder.v"
module fa_tb;
 reg a, b, c;
 wire s, c_out;
 
 full_adder fa(a, b, c, s, c_out);
 
 initial begin
      $dumpfile("Full_adder.vcd");
    $dumpvars(1,fa_tb);
 $monitor("At time %0t: a=%b b=%b, cin=%b, sum=%b, carry=%b",$time,
a,b,c,s,c_out);
 a = 0; b = 0; c = 0; #1;
 a = 0; b = 0; c = 1; #1;
 a = 0; b = 1; c = 0; #1;
 a = 0; b = 1; c = 1; #1;
 a = 1; b = 0; c = 0; #1;
 a = 1; b = 0; c = 1; #1;
 a = 1; b = 1; c = 0; #1;
 a = 1; b = 1; c = 1;
 end
endmodule

Full_adder/Full_adder.vcd
$date
	Sat Jul 13 12:52:32 2024
$end
$version
	Icarus Verilog
$end
$timescale
	1ps
$end
$scope module fa_tb $end
$var wire 1 ! c_out $end
$var wire 1 " s $end
$var reg 1 # a $end
$var reg 1 $ b $end
$var reg 1 % c $end
$upscope $end
$enddefinitions $end
#0
$dumpvars
0%
0$
0#
0"
0!
$end
#1000
1"
1%
#2000
0%
1$
#3000
1!
0"
1%
#4000
1"
0!
0%
0$
1#
#5000
0"
1%
#6000
0%
1$
#7000
1"
1%
